DBDictionary/MongoDb.py
DBDictionary/MySqlDb.py
DBDictionary/__init__.py
development/__init__.py
development/model.py
DBDictionary-0.1.1.dist-info/LICENSE.txt
DBDictionary-0.1.1.dist-info/METADATA
DBDictionary-0.1.1.dist-info/WHEEL
DBDictionary-0.1.1.dist-info/top_level.txt
DBDictionary-0.1.1.dist-info/RECORD
