Metadata-Version: 2.1
Name: DBDictionary
Version: 0.1.1
Summary: A dictionary-like interface for using databases
Author: shashstormer
Project-URL: GitHub, https://github.com/shashstormer/db_dict
Classifier: Development Status :: 4 - Beta
Classifier: Intended Audience :: Developers
Classifier: License :: OSI Approved :: MIT License
Classifier: Programming Language :: Python :: 3
Classifier: Programming Language :: Python :: 3.6
Classifier: Programming Language :: Python :: 3.7
Classifier: Programming Language :: Python :: 3.8
Classifier: Programming Language :: Python :: 3.9
Classifier: Topic :: Software Development :: Libraries
Classifier: Topic :: Database
License-File: LICENSE.txt
Requires-Dist: pymongo
Requires-Dist: mysql-connector-python
